pymine_net/__init__.py
pymine_net/enums.py
pymine_net/errors.py
pymine_net/net/asyncio/__init__.py
pymine_net/net/asyncio/client.py
pymine_net/net/asyncio/server.py
pymine_net/net/asyncio/stream.py
pymine_net/net/client.py
pymine_net/net/server.py
pymine_net/net/socket/__init__.py
pymine_net/net/socket/client.py
pymine_net/net/socket/server.py
pymine_net/net/socket/stream.py
pymine_net/net/stream.py
pymine_net/packets/__init__.py
pymine_net/packets/v_1_18_1/handshaking/handshake.py
pymine_net/packets/v_1_18_1/login/compression.py
pymine_net/packets/v_1_18_1/login/login.py
pymine_net/packets/v_1_18_1/play/advancement.py
pymine_net/packets/v_1_18_1/play/animations.py
pymine_net/packets/v_1_18_1/play/beacon.py
pymine_net/packets/v_1_18_1/play/block.py
pymine_net/packets/v_1_18_1/play/boss.py
pymine_net/packets/v_1_18_1/play/chat.py
pymine_net/packets/v_1_18_1/play/command.py
pymine_net/packets/v_1_18_1/play/command_block.py
pymine_net/packets/v_1_18_1/play/cooldown.py
pymine_net/packets/v_1_18_1/play/crafting.py
pymine_net/packets/v_1_18_1/play/difficulty.py
pymine_net/packets/v_1_18_1/play/effect.py
pymine_net/packets/v_1_18_1/play/entity.py
pymine_net/packets/v_1_18_1/play/explosion.py
pymine_net/packets/v_1_18_1/play/keep_alive.py
pymine_net/packets/v_1_18_1/play/map.py
pymine_net/packets/v_1_18_1/play/particle.py
pymine_net/packets/v_1_18_1/play/player_list.py
pymine_net/packets/v_1_18_1/status/status.py
pymine_net/strict_abc.py
pymine_net/types/block_palette.py
pymine_net/types/buffer.py
pymine_net/types/chat.py
pymine_net/types/nbt.py
pymine_net/types/packet.py
pymine_net/types/packet_map.py
pymine_net/types/registry.py
pymine_net-0.2.2.dist-info/LICENSE
pymine_net-0.2.2.dist-info/WHEEL
pymine_net-0.2.2.dist-info/METADATA
pymine_net-0.2.2.dist-info/RECORD
