Metadata-Version: 2.1
Name: pymine-net
Version: 0.2.2
Summary: Networking library for Minecraft in Python
Home-page: https://github.com/py-mine/pymine-net
License: LGPLv3
Keywords: Minecraft,protocol,networking
Author: PyMine-Net Developers & Contributors
Requires-Python: >=3.7,<4.0
Classifier: License :: Other/Proprietary License
Classifier: Programming Language :: Python :: 3
Classifier: Programming Language :: Python :: 3.10
Classifier: Programming Language :: Python :: 3.7
Classifier: Programming Language :: Python :: 3.8
Classifier: Programming Language :: Python :: 3.9
Requires-Dist: cryptography (>=36.0.1,<37.0.0)
Requires-Dist: mutf8 (>=1.0.6,<2.0.0)
Project-URL: Repository, https://github.com/py-mine/pymine-net
